langgraph/checkpoint/mssql/__init__.py
langgraph/checkpoint/mssql/aio.py
langgraph/checkpoint/mssql/base.py
langgraph/checkpoint/mssql/py.typed
langgraph_checkpoint_mssql-0.1.0.dist-info/METADATA
langgraph_checkpoint_mssql-0.1.0.dist-info/WHEEL
langgraph_checkpoint_mssql-0.1.0.dist-info/licenses/LICENSE
langgraph_checkpoint_mssql-0.1.0.dist-info/RECORD
