Metadata-Version: 2.4
Name: langgraph-checkpoint-mssql
Version: 0.1.0
Summary: Library with a MSSQL implementation of LangGraph checkpoint saver.
Project-URL: Repository, https://github.com/liminityab/langgraph-checkpoint-mssql
Author: Liminity AB
License-Expression: MIT
License-File: LICENSE
Keywords: checkpoint,langchain,langgraph,mssql,sqlserver
Classifier: Development Status :: 4 - Beta
Classifier: Intended Audience :: Developers
Classifier: License :: OSI Approved :: MIT License
Classifier: Programming Language :: Python :: 3.12
Requires-Python: >=3.12
Requires-Dist: aioodbc>=0.5.0
Requires-Dist: langgraph-checkpoint>=3.0.1
Requires-Dist: pyodbc>=5.3.0
